FlexiSpiderTools/__init__.py
FlexiSpiderTools/flexi_tools.py
FlexiSpiderTools-0.1.6.dist-info/LICENSE
FlexiSpiderTools-0.1.6.dist-info/METADATA
FlexiSpiderTools-0.1.6.dist-info/WHEEL
FlexiSpiderTools-0.1.6.dist-info/top_level.txt
FlexiSpiderTools-0.1.6.dist-info/RECORD
