Metadata-Version: 2.1
Name: FlexiSpiderTools
Version: 0.1.6
Summary: 一个用于爬虫的工具包
Home-page: 
Author: chengming
Author-email: 863493479@qq.com
Classifier: Programming Language :: Python :: 3
Classifier: License :: OSI Approved :: MIT License
Classifier: Operating System :: OS Independent
Requires-Python: >=3.8
License-File: LICENSE
Requires-Dist: Faker<31.0.0,>=30.6.0
Requires-Dist: loguru>=0.7.2
Requires-Dist: Requests>=2.32.3
Requires-Dist: setuptools<76.0.0,>=56.0.0
